LICENSE.txt
MANIFEST.in
README.txt
setup.py
bin/collage-create
collage/__init__.py
collage/base.py
collage/collager.py
collage/main.py
collage/search.py
collage.egg-info/PKG-INFO
collage.egg-info/SOURCES.txt
collage.egg-info/dependency_links.txt
collage.egg-info/requires.txt
collage.egg-info/top_level.txt
collage/test/__init__.py
collage/test/base.py
collage/test/test_base.py
collage/test/test_collager.py
collage/test/test_main.py
collage/test/test_search.py