Metadata-Version: 1.1
Name: collage
Version: 0.1.0
Summary: Creates collages of miniature images that resemble original downloaded from Google Images.
Home-page: http://pypi.python.org/pypi/collage/
Author: John Bywater
Author-email: jabywater@gmail.com
License: LICENSE.txt
Platform: UNKNOWN
Classifier: Development Status :: 4 - Beta
Classifier: Environment :: Console
Classifier: Intended Audience :: Developers
Classifier: License :: OSI Approved :: GNU Affero General Public License v3
Classifier: Operating System :: OS Independent
Classifier: Programming Language :: Python
Classifier: Topic :: Games/Entertainment
